setup.py
schemalib/__init__.py
schemalib.egg-info/PKG-INFO
schemalib.egg-info/SOURCES.txt
schemalib.egg-info/dependency_links.txt
schemalib.egg-info/requires.txt
schemalib.egg-info/top_level.txt