Metadata-Version: 1.0
Name: schemalib
Version: 1.0
Summary: Library for working with JSON Schemas
Home-page: https://github.com/shaded-enmity/schemalib
Author: Pavel Odvody
Author-email: podvody@redhat.com
License: GPLv-3
Keywords: lib
Platform: UNKNOWN
